tlq_client/__init__.py
tlq_client/client.py
tlq_client/exceptions.py
tlq_client/models.py
tlq_client-0.2.0.dist-info/licenses/LICENSE
tlq_client-0.2.0.dist-info/METADATA
tlq_client-0.2.0.dist-info/WHEEL
tlq_client-0.2.0.dist-info/top_level.txt
tlq_client-0.2.0.dist-info/RECORD
