Metadata-Version: 2.4
Name: tlq-client
Version: 0.2.0
Summary: Python client library for TLQ (Tiny Little Queue)
Author-email: Nebojsa Jakovljevic <nebojsa@skyak.tech>
License: MIT
Project-URL: Homepage, https://github.com/skyaktech/tlq-client-py
Project-URL: Repository, https://github.com/skyaktech/tlq-client-py
Project-URL: Issues, https://github.com/skyaktech/tlq-client-py/issues
Keywords: queue,message-queue,tlq,microservices
Classifier: Development Status :: 4 - Beta
Classifier: Intended Audience :: Developers
Classifier: License :: OSI Approved :: MIT License
Classifier: Programming Language :: Python :: 3
Classifier: Programming Language :: Python :: 3.7
Classifier: Programming Language :: Python :: 3.8
Classifier: Programming Language :: Python :: 3.9
Classifier: Programming Language :: Python :: 3.10
Classifier: Programming Language :: Python :: 3.11
Classifier: Programming Language :: Python :: 3.12
Classifier: Topic :: Software Development :: Libraries :: Python Modules
Classifier: Topic :: System :: Distributed Computing
Requires-Python: >=3.7
License-File: LICENSE
Requires-Dist: requests>=2.25.0
Provides-Extra: dev
Requires-Dist: pytest>=6.0; extra == "dev"
Requires-Dist: pytest-cov>=2.0; extra == "dev"
Requires-Dist: black>=21.0; extra == "dev"
Requires-Dist: isort>=5.0; extra == "dev"
Requires-Dist: flake8>=3.8; extra == "dev"
Requires-Dist: mypy>=0.800; extra == "dev"
Dynamic: license-file
